.gitattributes
.gitignore
.pre-commit-config.yaml
.readthedocs.yml
AUTHORS.rst
CODE_OF_CONDUCT.md
LICENSE.md
MANIFEST.in
README.md
conftest.py
pyproject.toml
pytest.ini
setup.py
.github/pull_request_template.md
.github/ISSUE_TEMPLATE/bug_report.md
.github/ISSUE_TEMPLATE/feature_request.md
.github/workflows/deploy.yml
.github/workflows/python-app.yml
.github/workflows/static.yml
docs/CONTRIBUTING.md
docs/Makefile
docs/make.bat
docs/source/API.rst
docs/source/conf.py
docs/source/index.rst
docs/source/advanced/abundances.ipynb
docs/source/advanced/advanced.rst
docs/source/advanced/config_options.rst
docs/source/advanced/creating_grids.rst
docs/source/advanced/units.ipynb
docs/source/emission_grids/grids.rst
docs/source/emission_grids/grids_example.ipynb
docs/source/emission_grids/grids_lines.ipynb
docs/source/emission_grids/grids_modify.ipynb
docs/source/emission_grids/pre-computed_grids.rst
docs/source/emission_models/combined_models.ipynb
docs/source/emission_models/custom_models.ipynb
docs/source/emission_models/dust_emission.ipynb
docs/source/emission_models/emission_models.rst
docs/source/emission_models/model_usage.ipynb
docs/source/emission_models/modify_models.ipynb
docs/source/emission_models/attenuation/attenuation.rst
docs/source/emission_models/attenuation/dust_attenuation.ipynb
docs/source/emission_models/attenuation/igm.ipynb
docs/source/emission_models/premade_models/agn_models.ipynb
docs/source/emission_models/premade_models/common_models.ipynb
docs/source/emission_models/premade_models/premade_models.rst
docs/source/emission_models/premade_models/stellar_models.ipynb
docs/source/emissions/emissions.rst
docs/source/emissions/emission_objects/lines_example.ipynb
docs/source/emissions/emission_objects/sed_example.ipynb
docs/source/emissions/lines/galaxy_lines.ipynb
docs/source/emissions/spectra/blackholes.ipynb
docs/source/emissions/spectra/galaxy.ipynb
docs/source/emissions/spectra/stars.ipynb
docs/source/galaxy_components/blackholes.ipynb
src/cosmos_synthesizer.egg-info/PKG-INFO
src/cosmos_synthesizer.egg-info/SOURCES.txt
src/cosmos_synthesizer.egg-info/dependency_links.txt
src/cosmos_synthesizer.egg-info/entry_points.txt
src/cosmos_synthesizer.egg-info/requires.txt
src/cosmos_synthesizer.egg-info/top_level.txt
