Metadata-Version: 2.4
Name: cosmos-synthesizer
Version: 0.11.0
Summary: A package for synthetic observations of the Universe
Author-email: "W. J. Roper" <w.roper@sussex.ac.uk>, "C. C. Lovell" <chris.lovell.astro@gmail.com>, "A. P. Vijayan" <A.Payyoor-Vijayan@sussex.ac.uk>, "S. M. Wilkins" <s.wilkins@sussex.ac.uk>, "S. Newman" <sophie.newman@port.ac.uk>, "T. Harvey" <thomas.harvey-3@manchester.ac.uk>, "L. Seeyave" <L.Seeyave@sussex.ac.uk>, "K. Iyer" <kartheikiyer@gmail.com>, "C. S. Fournier" <connor.sant.17@um.edu.mt>
Maintainer-email: "C. C. Lovell" <chris.lovell.astro@gmail.com>, "W. J. Roper" <w.roper@sussex.ac.uk>, "A. P. Vijayan" <A.Payyoor-Vijayan@sussex.ac.uk>, "S. M. Wilkins" <s.wilkins@sussex.ac.uk>
License:                     GNU GENERAL PUBLIC LICENSE
Project-URL: Homepage, https://github.com/synthesizer-project/synthesizer
Project-URL: Bug Reports, https://github.com/synthesizer-project/synthesizer/issues
Project-URL: Source, https://github.com/synthesizer-project/synthesizer
Project-URL: Documentation, https://synthesizer-project.github.io/synthesizer/
Keywords: galaxy,modelling,smoothed particle hydrodynamics,particles,nbody,galaxy formation,parametric,theory,sph,cosmology,galaxy evolution,survey,space telescope,SED,sed,spectral energy distribution,stellar population,synthesis
Classifier: Development Status :: 5 - Production/Stable
Classifier: Intended Audience :: Science/Research
Classifier: Topic :: Scientific/Engineering :: Astronomy
Classifier: License :: OSI Approved :: GNU General Public License v3 (GPLv3)
Classifier: Programming Language :: Python :: 3.10
Classifier: Programming Language :: Python :: 3.11
Classifier: Programming Language :: Python :: 3.12
Classifier: Programming Language :: Python :: 3.13
Classifier: Programming Language :: Python :: 3 :: Only
Requires-Python: >=3.10
License-File: LICENSE.md
License-File: AUTHORS.rst
Requires-Dist: setuptools
Requires-Dist: astropy
Requires-Dist: h5py
Requires-Dist: numpy>=1.23
Requires-Dist: packaging
Requires-Dist: scipy
Requires-Dist: unyt
Requires-Dist: cmasher
Requires-Dist: dust_extinction>=1.6
Requires-Dist: matplotlib
Requires-Dist: spectres
Requires-Dist: tqdm
Requires-Dist: requests
Requires-Dist: pathos
Requires-Dist: statsmodels
Requires-Dist: pympler
Requires-Dist: platformdirs
Provides-Extra: dev
Requires-Dist: ruff==0.11.7; extra == "dev"
Requires-Dist: pre-commit; extra == "dev"
Requires-Dist: nb-clean; extra == "dev"
Provides-Extra: test
Requires-Dist: nbmake; extra == "test"
Requires-Dist: pytest; extra == "test"
Requires-Dist: ruff==0.11.7; extra == "test"
Requires-Dist: mypy>=0.910; extra == "test"
Provides-Extra: docs
Requires-Dist: nbmake; extra == "docs"
Requires-Dist: sphinx==7.4.7; extra == "docs"
Requires-Dist: pandoc; extra == "docs"
Requires-Dist: furo; extra == "docs"
Requires-Dist: sphinx_autodoc_typehints; extra == "docs"
Requires-Dist: ipython; extra == "docs"
Requires-Dist: sphinx_gallery; extra == "docs"
Requires-Dist: pillow; extra == "docs"
Requires-Dist: sphinx-toolbox; extra == "docs"
Requires-Dist: nbsphinx; extra == "docs"
Requires-Dist: sphinx-copybutton; extra == "docs"
Requires-Dist: readthedocs-sphinx-search; extra == "docs"
Provides-Extra: bluetides
Requires-Dist: bigfile; extra == "bluetides"
Provides-Extra: eagle
Requires-Dist: schwimmbad; extra == "eagle"
Dynamic: license-file
